LICENSE
MANIFEST.in
README.md
setup.cfg
setup.py
djongo/__init__.py
djongo/admin.py
djongo/base.py
djongo/compiler.py
djongo/creation.py
djongo/cursor.py
djongo/database.py
djongo/exceptions.py
djongo/features.py
djongo/introspection.py
djongo/operations.py
djongo/schema.py
djongo/storage.py
djongo/transaction.py
djongo/utils.py
djongo/dynamic_formsets/__init__.py
djongo/dynamic_formsets/apps.py
djongo/dynamic_formsets/static/dynamic_formsets/images/add.png
djongo/dynamic_formsets/static/dynamic_formsets/images/delete.png
djongo/dynamic_formsets/static/dynamic_formsets/js/jquery/jquery.js
djongo/dynamic_formsets/static/dynamic_formsets/js/jquery/jquery.min.js
djongo/dynamic_formsets/static/dynamic_formsets/js/jquery/jquery.min.map
djongo/dynamic_formsets/static/dynamic_formsets/js/jquery/jquery.slim.js
djongo/dynamic_formsets/static/dynamic_formsets/js/jquery/jquery.slim.min.js
djongo/dynamic_formsets/static/dynamic_formsets/js/jquery/jquery.slim.min.map
djongo/dynamic_formsets/static/dynamic_formsets/js/jquery-formset/jquery.formset.js
djongo/dynamic_formsets/static/dynamic_formsets/js/jquery-formset/jquery.formset.min.js
djongo/dynamic_formsets/templates/admin/change_form.html
djongo/dynamic_formsets/templatetags/__init__.py
djongo/dynamic_formsets/templatetags/formset_tags.py
djongo/models/__init__.py
djongo/models/fields.py
djongo/models/indexes.py
djongo/models/json.py
djongo/sql2mongo/__init__.py
djongo/sql2mongo/aggregation.py
djongo/sql2mongo/constraints.py
djongo/sql2mongo/converters.py
djongo/sql2mongo/functions.py
djongo/sql2mongo/operators.py
djongo/sql2mongo/query.py
djongo/sql2mongo/sql_tokens.py
djongo/sql2mongo/validation.py
us2djongo.egg-info/PKG-INFO
us2djongo.egg-info/SOURCES.txt
us2djongo.egg-info/dependency_links.txt
us2djongo.egg-info/requires.txt
us2djongo.egg-info/top_level.txt