Metadata-Version: 2.1
Name: us2djongo
Version: 1.3.44
Summary: Driver for allowing Django to use MongoDB as the database backend.
Home-page: https://github.com/morbitech1/djongo
Author: nesdis
Author-email: nesdis@gmail.com
License: AGPL
Keywords: Django MongoDB driver connector
Classifier: Development Status :: 3 - Alpha
Classifier: Intended Audience :: Developers
Classifier: License :: OSI Approved :: BSD License
Classifier: Programming Language :: Python :: 3.6
Requires-Python: >=3.6
Provides-Extra: json
License-File: LICENSE
